{
    "session_id": "608446041102674707.1626008338.1626008338",
    "client_id": "141664883.1626008339",
    "visit_date": "2021-07-11",
    "visit_time": "15:00:00",
    "visit_number": 1,
    "utm_source": "geDcueAOghDzHkGMmdOq",
    "utm_medium": "cpm",
    "utm_campaign": "FTjNLDyTrXaWYgZymFkV",
    "utm_adcontent": "WYLajZgbUhGimwBKDZUH",
    "utm_keyword": null,
    "device_category": "tablet",
    "device_os": null,
    "device_brand": "Samsung",
    "device_model": null,
    "device_screen_resolution": "800x1280",
    "device_browser": "Android Webview",
    "geo_country": "Russia",
    "geo_city": "Belgorod",
    "target_event_action": 0
}