{
    "session_id": "3132340618625671308.1622541120.1622541120",
    "client_id": "729304882.1622532236",
    "visit_date": "2021-06-01",
    "visit_time": "12:00:00",
    "visit_number": 2,
    "utm_source": "fDLlAcSmythWSCVMvqvL",
    "utm_medium": "(none)",
    "utm_campaign": "LTuZkdKfxRGVceoWkVyg",
    "utm_adcontent": "JNHcPlZPxEMWDnRiyoBf",
    "utm_keyword": null,
    "device_category": "desktop",
    "device_os": null,
    "device_brand": "",
    "device_model": null,
    "device_screen_resolution": "3440x1440",
    "device_browser": "Chrome",
    "geo_country": "Russia",
    "geo_city": "Moscow",
    "target_event_action": 1
}